Metadata-Version: 1.1
Name: FlaskIt-starter
Version: 1.0.0
Summary: Flask API starter
Home-page: https://github.com/connormullett/FlaskIt
Author: Connor Mullett
Author-email: UNKNOWN
License: MIT
Download-URL: https://github.com/connormullett/FlaskIt/archive/v1.0.tar.gz
Keywords: flask api
Platform: UNKNOWN
